aa_ml/__init__.py
aa_ml/aml_pipeline.py
andreani_aa_ml-0.0.1.dist-info/LICENSE
andreani_aa_ml-0.0.1.dist-info/METADATA
andreani_aa_ml-0.0.1.dist-info/WHEEL
andreani_aa_ml-0.0.1.dist-info/top_level.txt
andreani_aa_ml-0.0.1.dist-info/RECORD
