Metadata-Version: 2.1
Name: andreani-aa-ml
Version: 0.0.1
Summary: Common functions for ML proyects used by the Andreani Advanced Analytics team
Home-page: https://github.com/eloychang/andreani_ml
Author-email: Eloy Chang <echang@andreani.com>
Maintainer-email: Ignacio Belogi <ibelogi@andreani.com>, Gabriel Aranda <garanda@andreani.com>, Mariana Liu <mliu@andreani.com>, Yasmin Ojeda <yojeda@andreani.com>, Ariel Fleiderman <afleiderman@andreani.com>, Daiana Alonso <dalonso@andreani.com>, Facundo Silvestre <fsilvestre@andreani.com>, Santiago Bergman <sbergman@andreani.com>, Matías Moyano <matmoyano@andreani.com>, Giuliana Vera <gvera@andreani.com>, Ezequiel Brodschi <ebrodschi@andreani.com>, Sol Cari <scari@andreani.com>
License: MIT License
Project-URL: Homepage, https://github.com/eloychang/andreani_ml
Project-URL: Bug Tracker, https://github.com/eloychang/andreani_ml/issues
Classifier: Programming Language :: Python :: 3
Classifier: License :: OSI Approved :: MIT License
Classifier: Operating System :: OS Independent
Requires-Python: >=3.7
License-File: LICENSE
Requires-Dist: azureml
Requires-Dist: azureml-core
Requires-Dist: azure-storage-blob
Requires-Dist: azure-storage-file-datalake
Requires-Dist: andreani-aa-tools
